sentry_dingtalk/__init__.py
sentry_dingtalk/plugin.py
sentry_dingtalk_ecool/__init__.py
sentry_dingtalk_ecool/plugin.py
sentry_dingtalk_ecool2/__init__.py
sentry_dingtalk_ecool2/plugin.py
sentry_dingtalk_ecool2-1.0.0.dist-info/METADATA
sentry_dingtalk_ecool2-1.0.0.dist-info/WHEEL
sentry_dingtalk_ecool2-1.0.0.dist-info/entry_points.txt
sentry_dingtalk_ecool2-1.0.0.dist-info/top_level.txt
sentry_dingtalk_ecool2-1.0.0.dist-info/RECORD
